Week 9/lib.v
module invert (input wire i, output wire o);
   assign o = !i;
endmodule

module and2 (input wire i0, i1, output wire o);
  assign o = i0 & i1;
endmodule

module or2 (input wire i0, i1, output wire o);
  assign o = i0 | i1;
endmodule

module xor2 (input wire i0, i1, output wire o);
  assign o = i0 ^ i1;
endmodule

module nand2 (input wire i0, i1, output wire o);
   wire t;
   and2 and2_0 (i0, i1, t);
   invert invert_0 (t, o);
endmodule

module nor2 (input wire i0, i1, output wire o);
   wire t;
   or2 or2_0 (i0, i1, t);
   invert invert_0 (t, o);
endmodule

module xnor2 (input wire i0, i1, output wire o);
   wire t;
   xor2 xor2_0 (i0, i1, t);
   invert invert_0 (t, o);
endmodule

module and3 (input wire i0, i1, i2, output wire o);
   wire t;
   and2 and2_0 (i0, i1, t);
   and2 and2_1 (i2, t, o);
endmodule

module or3 (input wire i0, i1, i2, output wire o);
   wire t;
   or2 or2_0 (i0, i1, t);
   or2 or2_1 (i2, t, o);
endmodule

module nor3 (input wire i0, i1, i2, output wire o);
   wire t;
   or2 or2_0 (i0, i1, t);
   nor2 nor2_0 (i2, t, o);
endmodule

module nand3 (input wire i0, i1, i2, output wire o);
   wire t;
   and2 and2_0 (i0, i1, t);
   nand2 nand2_1 (i2, t, o);
endmodule

module xor3 (input wire i0, i1, i2, output wire o);
   wire t;
   xor2 xor2_0 (i0, i1, t);
   xor2 xor2_1 (i2, t, o);
endmodule

module xnor3 (input wire i0, i1, i2, output wire o);
   wire t;
   xor2 xor2_0 (i0, i1, t);
   xnor2 xnor2_0 (i2, t, o);
endmodule

module mux2 (input wire i0, i1, j, output wire o);
  assign o = (j==0)?i0:i1;
endmodule

module mux3 (input wire [0:2] i, input wire j1, j0, output wire o);
  wire  t;
  mux2 mux2_0 (i[0], i[1], j0, t);
  mux2 mux2_1 (t, i[2], j1, o);
endmodule

module mux4 (input wire [0:3] i, input wire j1, j0, output wire o);
  wire  t0, t1;
  mux2 mux2_0 (i[0], i[1], j1, t0);
  mux2 mux2_1 (i[2], i[3], j1, t1);
  mux2 mux2_2 (t0, t1, j0, o);
endmodule

module mux8 (input wire [0:7] i, input wire j2, j1, j0, output wire o);
  wire  t0, t1;
  mux4 mux4_0 (i[0:3], j2, j1, t0);
  mux4 mux4_1 (i[4:7], j2, j1, t1);
  mux2 mux2_0 (t0, t1, j0, o);
endmodule

module demux2 (input wire i, j, output wire o0, o1);
  assign o0 = (j==0)?i:1'b0;
  assign o1 = (j==1)?i:1'b0;
endmodule

module demux4 (input wire i, j1, j0, output wire [0:3] o);
  wire  t0, t1;
  demux2 demux2_0 (i, j1, t0, t1);
  demux2 demux2_1 (t0, j0, o[0], o[1]);
  demux2 demux2_2 (t1, j0, o[2], o[3]);
endmodule

module demux8 (input wire i, j2, j1, j0, output wire [0:7] o);
  wire  t0, t1;
  demux2 demux2_0 (i, j2, t0, t1);
  demux4 demux4_0 (t0, j1, j0, o[0:3]);
  demux4 demux4_1 (t1, j1, j0, o[4:7]);
endmodule

module df (input wire clk, in, output wire out);
  reg df_out;
  always@(posedge clk) df_out <= in;
  assign out = df_out;
endmodule

module dfr (input wire clk, reset, in, output wire out);
  wire reset_, df_in;
  invert invert_0 (reset, reset_);
  and2 and2_0 (in, reset_, df_in);
  df df_0 (clk, df_in, out);
endmodule

module dfrl (input wire clk, reset, load, in, output wire out);
  wire _in;
  mux2 mux2_0(out, in, load, _in);
  dfr dfr_1(clk, reset, _in, out);
endmodule

module dfs (input wire clk, set, in, output wire out);
  wire dfr_in,dfr_out;
  invert invert_0(in, dfr_in);
  invert invert_1(dfr_out, out);
  dfr dfr_2(clk, set, dfr_in, dfr_out);
endmodule

module dfsl (input wire clk, set, load, in, output wire out);
  wire _in;
  mux2 mux2_0(out, in, load, _in);
  dfs dfs_1(clk, set, _in, out);
endmodule

module fa (input wire i0, i1, cin, output wire sum, cout);
   wire t0, t1, t2;
   xor3 _i0 (i0, i1, cin, sum);
   and2 _i1 (i0, i1, t0);
   and2 _i2 (i1, cin, t1);
   and2 _i3 (cin, i0, t2);
   or3 _i4 (t0, t1, t2, cout);
endmodule

module addsub (input wire addsub, i0, i1, cin, output wire sumdiff, cout);
  wire t;
  fa _i0 (i0, t, cin, sumdiff, cout);
  xor2 _i1 (i1, addsub, t);
endmodule

Week 2/add.v
//Module full adder.
module fulladd(input wire a,b,c, output wire s,cout);
	wire t0,t1,t2,t3,t4;
	xor2 x0(a,b,t0);
	xor2 x1(t0,c,s);
	and2 a0(a,b,t1);
	and2 a1(a,c,t2);
	and2 a2(b,c,t3);
	or2 o1(t1,t2,t4);
	or2 o2(t3,t4,cout);
endmodule

// Module 4-bit ripple carry adder.

module fa4 (input wire [3:0] a, b, input wire cin, output wire [3:0] sum, output wire cout);
	wire[2:0] t;
	fulladd fa0(a[0],b[0],1'b0,sum[0],t[0]);
	fulladd fa1(a[1],b[1],t[0],sum[1],t[1]);
	fulladd fa2(a[2],b[2],t[1],sum[2],t[2]);
	fulladd fa3(a[3],b[3],t[2],sum[3],cout);
endmodule

Week 2/tb_add.v
`timescale 1 ns / 100 ps
`define TESTVECS 8

module tb;
  reg clk, reset;
  reg [3:0] i0, i1; reg cin;
  wire [3:0] o; wire cout;
  reg [8:0] test_vecs [0:(`TESTVECS-1)];
  integer i;
  initial begin $dumpfile("tb_add.vcd"); $dumpvars(0,tb); end
  initial begin reset = 1'b1; #12.5 reset = 1'b0; end
  initial clk = 1'b0; always #5 clk =~ clk;
  initial begin
    test_vecs[0] = 9'b000000010;
    test_vecs[1] = 9'b000100010;
    test_vecs[2] = 9'b011100010;
    test_vecs[3] = 9'b000001110;
    test_vecs[4] = 9'b011001111;
    test_vecs[5] = 9'b001110011;
    test_vecs[6] = 9'b111100011;
    test_vecs[7] = 9'b011101110;
  end
  initial {i0, i1, cin} = 0;
  fa4 u0 (i0, i1, cin, o, cout);
  initial begin
    #6 for(i=0;i<`TESTVECS;i=i+1)
      begin #10 {i0, i1, cin}=test_vecs[i]; end
    #100 $finish;
  end
endmodule

Week 2/tb_add.vcd
$date
	Sat Sep 14 13:37:47 2019
$end
$version
	Icarus Verilog
$end
$timescale
	100ps
$end
$scope module tb $end
$var wire 1 ! cout $end
$var wire 4 " o [3:0] $end
$var reg 1 # cin $end
$var reg 1 $ clk $end
$var integer 32 % i [31:0] $end
$var reg 4 & i0 [3:0] $end
$var reg 4 ' i1 [3:0] $end
$var reg 1 ( reset $end
$scope module u0 $end
$var wire 4 ) a [3:0] $end
$var wire 4 * b [3:0] $end
$var wire 1 + cin $end
$var wire 1 ! cout $end
$var wire 4 , sum [3:0] $end
$var wire 3 - t [2:0] $end
$scope module fa0 $end
$var wire 1 . a $end
$var wire 1 / b $end
$var wire 1 0 c $end
$var wire 1 1 cout $end
$var wire 1 2 s $end
$var wire 1 3 t0 $end
$var wire 1 4 t1 $end
$var wire 1 5 t2 $end
$var wire 1 6 t3 $end
$var wire 1 7 t4 $end
$scope module x0 $end
$var wire 1 . i0 $end
$var wire 1 / i1 $end
$var wire 1 3 o $end
$upscope $end
$scope module x1 $end
$var wire 1 3 i0 $end
$var wire 1 0 i1 $end
$var wire 1 2 o $end
$upscope $end
$scope module a0 $end
$var wire 1 . i0 $end
$var wire 1 / i1 $end
$var wire 1 4 o $end
$upscope $end
$scope module a1 $end
$var wire 1 . i0 $end
$var wire 1 0 i1 $end
$var wire 1 5 o $end
$upscope $end
$scope module a2 $end
$var wire 1 / i0 $end
$var wire 1 0 i1 $end
$var wire 1 6 o $end
$upscope $end
$scope module o1 $end
$var wire 1 4 i0 $end
$var wire 1 5 i1 $end
$var wire 1 7 o $end
$upscope $end
$scope module o2 $end
$var wire 1 6 i0 $end
$var wire 1 7 i1 $end
$var wire 1 1 o $end
$upscope $end
$upscope $end
$scope module fa1 $end
$var wire 1 8 a $end
$var wire 1 9 b $end
$var wire 1 : c $end
$var wire 1 ; cout $end
$var wire 1 < s $end
$var wire 1 = t0 $end
$var wire 1 > t1 $end
$var wire 1 ? t2 $end
$var wire 1 @ t3 $end
$var wire 1 A t4 $end
$scope module x0 $end
$var wire 1 8 i0 $end
$var wire 1 9 i1 $end
$var wire 1 = o $end
$upscope $end
$scope module x1 $end
$var wire 1 = i0 $end
$var wire 1 : i1 $end
$var wire 1 < o $end
$upscope $end
$scope module a0 $end
$var wire 1 8 i0 $end
$var wire 1 9 i1 $end
$var wire 1 > o $end
$upscope $end
$scope module a1 $end
$var wire 1 8 i0 $end
$var wire 1 : i1 $end
$var wire 1 ? o $end
$upscope $end
$scope module a2 $end
$var wire 1 9 i0 $end
$var wire 1 : i1 $end
$var wire 1 @ o $end
$upscope $end
$scope module o1 $end
$var wire 1 > i0 $end
$var wire 1 ? i1 $end
$var wire 1 A o $end
$upscope $end
$scope module o2 $end
$var wire 1 @ i0 $end
$var wire 1 A i1 $end
$var wire 1 ; o $end
$upscope $end
$upscope $end
$scope module fa2 $end
$var wire 1 B a $end
$var wire 1 C b $end
$var wire 1 D c $end
$var wire 1 E cout $end
$var wire 1 F s $end
$var wire 1 G t0 $end
$var wire 1 H t1 $end
$var wire 1 I t2 $end
$var wire 1 J t3 $end
$var wire 1 K t4 $end
$scope module x0 $end
$var wire 1 B i0 $end
$var wire 1 C i1 $end
$var wire 1 G o $end
$upscope $end
$scope module x1 $end
$var wire 1 G i0 $end
$var wire 1 D i1 $end
$var wire 1 F o $end
$upscope $end
$scope module a0 $end
$var wire 1 B i0 $end
$var wire 1 C i1 $end
$var wire 1 H o $end
$upscope $end
$scope module a1 $end
$var wire 1 B i0 $end
$var wire 1 D i1 $end
$var wire 1 I o $end
$upscope $end
$scope module a2 $end
$var wire 1 C i0 $end
$var wire 1 D i1 $end
$var wire 1 J o $end
$upscope $end
$scope module o1 $end
$var wire 1 H i0 $end
$var wire 1 I i1 $end
$var wire 1 K o $end
$upscope $end
$scope module o2 $end
$var wire 1 J i0 $end
$var wire 1 K i1 $end
$var wire 1 E o $end
$upscope $end
$upscope $end
$scope module fa3 $end
$var wire 1 L a $end
$var wire 1 M b $end
$var wire 1 N c $end
$var wire 1 ! cout $end
$var wire 1 O s $end
$var wire 1 P t0 $end
$var wire 1 Q t1 $end
$var wire 1 R t2 $end
$var wire 1 S t3 $end
$var wire 1 T t4 $end
$scope module x0 $end
$var wire 1 L i0 $end
$var wire 1 M i1 $end
$var wire 1 P o $end
$upscope $end
$scope module x1 $end
$var wire 1 P i0 $end
$var wire 1 N i1 $end
$var wire 1 O o $end
$upscope $end
$scope module a0 $end
$var wire 1 L i0 $end
$var wire 1 M i1 $end
$var wire 1 Q o $end
$upscope $end
$scope module a1 $end
$var wire 1 L i0 $end
$var wire 1 N i1 $end
$var wire 1 R o $end
$upscope $end
$scope module a2 $end
$var wire 1 M i0 $end
$var wire 1 N i1 $end
$var wire 1 S o $end
$upscope $end
$scope module o1 $end
$var wire 1 Q i0 $end
$var wire 1 R i1 $end
$var wire 1 T o $end
$upscope $end
$scope module o2 $end
$var wire 1 S i0 $end
$var wire 1 T i1 $end
$var wire 1 ! o $end
$upscope $end
$upscope $end
$upscope $end
$upscope $end
$enddefinitions $end
#0
$dumpvars
0T
0S
0R
0Q
0P
0O
0N
0M
0L
0K
0J
0I
0H
0G
0F
0E
0D
0C
0B
0A
0@
0?
0>
0=
0<
0;
0:
09
08
07
06
05
04
03
02
01
00
0/
0.
b0 -
b0 ,
0+
b0 *
b0 )
1(
b0 '
b0 &
bx %
0$
0#
b0 "
0!
$end
#50
1$
#60
b0 %
#100
0$
#125
0(
#150
1$
#160
12
b1 "
b1 ,
13
1/
b1 %
b1 '
b1 *
#200
0$
#250
1$
#260
1<
1:
11
b1 -
02
b10 "
b10 ,
17
03
14
1.
b10 %
b1 &
b1 )
#300
0$
#350
1$
#360
1O
1N
1E
1K
1I
1D
1;
b111 -
0<
1A
0F
b1000 "
b1000 ,
1=
1?
1G
18
1B
b11 %
b111 &
b111 )
#400
0$
#450
1$
#460
0O
0N
0E
1F
0D
0;
1<
0:
01
b0 -
12
b111 "
b111 ,
07
0A
0K
13
04
0?
0I
0@
0J
0.
08
0B
19
1C
b100 %
b0 &
b0 )
b111 '
b111 *
#500
0$
#550
1$
#560
1I
1J
1O
1D
1N
1;
1E
b110 -
0<
1A
1F
b1101 "
b1101 ,
1K
0=
1>
0G
1H
18
1B
b101 %
b110 &
b110 )
1#
1+
#600
0$
#650
1$
#660
1?
1F
1:
1D
0N
11
1;
0E
b11 -
02
17
0<
1A
0K
1O
b1100 "
b1100 ,
0!
03
14
0I
1=
0>
0H
0J
1P
0S
1.
0B
09
0C
1M
b110 %
b11 &
b11 )
b1001 '
b1001 *
#700
0$
#750
1$
#760
1!
1T
0O
1R
1N
1E
b111 -
0F
b0 "
b0 ,
1K
1G
1I
1B
1L
0M
b111 %
b1111 &
b1111 )
b1 '
b1 *
#800
0$
#850
1$
#860
0!
1O
0T
1<
1F
b1110 "
b1110 ,
0P
0R
0=
1>
1@
0G
1H
1J
0L
19
1C
b1000 %
b111 &
b111 )
b111 '
b111 *
0#
0+
